{
  "measurements": [
    {
      "date/yyyy-mm-dd": "2024-06-04",
      "stamps": [
        {
          "time_start/hh:mm:ss": "17:00:00",
          "time_end/hh:mm:ss": "17:02:00"
        },
        {
          "time_start/hh:mm:ss": "16:57:00",
          "time_end/hh:mm:ss": "16:59:00"
        },
        {
          "time_start/hh:mm:ss": "16:54:00",
          "time_end/hh:mm:ss": "16:56:00"
        },
        {
          "time_start/hh:mm:ss": "16:51:00",
          "time_end/hh:mm:ss": "16:53:00"
        }
      ]
    },
    {
      "date/yyyy-mm-dd": "2024-06-06",
      "fluid": [
        "Methane",
        "Carbon Dioxide"
      ],
      "stamps": [
        {
          "time_start/hh:mm:ss": "08:42:00",
          "time_end/hh:mm:ss": "08:44:00"
        },
        {
          "time_start/hh:mm:ss": "08:39:00",
          "time_end/hh:mm:ss": "08:41:00"
        },
        {
          "time_start/hh:mm:ss": "08:36:00",
          "time_end/hh:mm:ss": "08:38:00"
        },
        {
          "time_start/hh:mm:ss": "08:31:00",
          "time_end/hh:mm:ss": "08:34:00"
        }
      ]
    }
  ]
}